MANIFEST.in
README.md
requirements.txt
setup.py
piction/Algorithm.py
piction/MakeFunction.py
piction/__init__.py
piction.egg-info/PKG-INFO
piction.egg-info/SOURCES.txt
piction.egg-info/dependency_links.txt
piction.egg-info/requires.txt
piction.egg-info/top_level.txt