Metadata-Version: 2.1
Name: piction
Version: 0.1
Summary: 絵を関数化するライブラリ
Home-page: https://github.com/hackathonNIT/piction
License: UNKNOWN
Platform: UNKNOWN
